circuits.v
// 1-bit NOT gate
module not_gate(input a, output y);
    assign y = ~a;
endmodule

// 1-bit NAND gate
module nand_gate(input a, input b, output y);
    assign y = ~(a & b);
endmodule

// 1-bit NOR gate
module nor_gate(input a, input b, output y);
    assign y = ~(a | b);
endmodule

// 1x4-bit Shift Circuit
module shift_circuit(input [3:0] data_in, input shift_right, output [3:0] data_out);
    assign data_out = shift_right ? {1'b0, data_in[3:1]} : {data_in[2:0], 1'b0};
endmodule

test.v
module tb;
    reg a, b;
    wire y_not, y_nand, y_nor;
    reg [3:0] data_in;
    wire [3:0] data_out;

    // Instantiate the circuits
    not_gate U1(a, y_not);
    nand_gate U2(a, b, y_nand);
    nor_gate U3(a, b, y_nor);
    shift_circuit U4(data_in, 1'b1, data_out); // Shift right

    // Test cases
    initial begin
        $dumpfile("waveform.vcd"); // Specify the VCD filename
        $dumpvars(0, tb);          // Dump all variables in the testbench

        // Test NOT gate
        a = 0; #10;
        $display("NOT(%b) = %b", a, y_not);
        a = 1; #10;
        $display("NOT(%b) = %b", a, y_not);

        // Test NAND gate
        a = 1; b = 0; #10;
        $display("NAND(%b, %b) = %b", a, b, y_nand);
        a = 1; b = 1; #10;
        $display("NAND(%b, %b) = %b", a, b, y_nand);

        // Test NOR gate
        a = 0; b = 1; #10;
        $display("NOR(%b, %b) = %b", a, b, y_nor);
        a = 0; b = 0; #10;
        $display("NOR(%b, %b) = %b", a, b, y_nor);

        // Test Shift Circuit
        data_in = 4'b1010; #10;
        $display("Shift right(%b) = %b", data_in, data_out);
        data_in = 4'b0101; #10;
        $display("Shift right(%b) = %b", data_in, data_out);

        
    end

    // iverilog -o tb.vvp circuits.v test.v
    // vvp tb.vvp
    // gtkwave waveform.vcd
endmodule

waveform.vcd
$date
	Wed Sep 25 05:43:04 2024
$end
$version
	Icarus Verilog
$end
$timescale
	1s
$end
$scope module tb $end
$var wire 1 ! y_not $end
$var wire 1 " y_nor $end
$var wire 1 # y_nand $end
$var wire 4 $ data_out [3:0] $end
$var reg 1 % a $end
$var reg 1 & b $end
$var reg 4 ' data_in [3:0] $end
$scope module U1 $end
$var wire 1 % a $end
$var wire 1 ! y $end
$upscope $end
$scope module U2 $end
$var wire 1 % a $end
$var wire 1 & b $end
$var wire 1 # y $end
$upscope $end
$scope module U3 $end
$var wire 1 % a $end
$var wire 1 & b $end
$var wire 1 " y $end
$upscope $end
$scope module U4 $end
$var wire 4 ( data_in [3:0] $end
$var wire 4 ) data_out [3:0] $end
$var wire 1 * shift_right $end
$upscope $end
$upscope $end
$enddefinitions $end
#0
$dumpvars
1*
b0xxx )
bx (
bx '
x&
0%
b0xxx $
1#
x"
1!
$end
#10
x#
0"
0!
1%
#20
1#
0&
#30
0#
1&
#40
1#
1!
0%
#50
1"
0&
#60
b101 $
b101 )
b1010 '
b1010 (
#70
b10 $
b10 )
b101 '
b101 (
